{
  "project_id": "project_1773490247620",
  "video": "2026 BAFL DIV1 - WEEK 2： BRUSSELS BLACK ANGELS @ WATERLOO WARRIORS [7uJVvT1tHFs].mp4",
  "match_info": {
    "date": "",
    "competition": "",
    "home": "",
    "away": "",
    "scout": "",
    "analyst": "",
    "venue": "",
    "season": "",
    "notes": ""
  },
  "items": [
    {
      "id": "play_i9ta4jbq",
      "kind": "play",
      "t": 0,
      "frame": 0
    },
    {
      "id": "play_uq9djne0",
      "kind": "play",
      "t": 0,
      "frame": 0
    },
    {
      "id": "event_2108fg0y",
      "kind": "event",
      "t": 0,
      "frame": 0
    }
  ],
  "params": {
    "play_i9ta4jbq": {
      "notes": "",
      "category": "Offensive",
      "quarter": "Q1",
      "down": "1",
      "ytg": "Medium",
      "fieldPos": "Own territory",
      "hash": "Middle",
      "qbAlign": "Shotgun",
      "receiverDist": "Balanced",
      "backfield": "Singleback",
      "motion": "None",
      "shift": "None",
      "playType": "Pass",
      "runConcept": "",
      "passDepth": "Short (0–10)",
      "passType": "Dropback",
      "direction": "Middle",
      "target": "",
      "yardGain": "",
      "yardCat": "",
      "success": "",
      "negEvents": [],
      "turnover": "None",
      "_wrCount": 0,
      "_rbCount": 0,
      "_teCount": 0,
      "_olCount": 0,
      "_qbCount": 0
    },
    "play_uq9djne0": {
      "notes": "",
      "category": "Offensive",
      "quarter": "Q1",
      "down": "1",
      "ytg": "Medium",
      "fieldPos": "Own territory",
      "hash": "Middle",
      "qbAlign": "Shotgun",
      "receiverDist": "Balanced",
      "backfield": "Singleback",
      "motion": "None",
      "shift": "None",
      "playType": "Pass",
      "runConcept": "",
      "passDepth": "Short (0–10)",
      "passType": "Dropback",
      "direction": "Middle",
      "target": "",
      "yardGain": "",
      "yardCat": "",
      "success": "",
      "negEvents": [],
      "turnover": "None",
      "_wrCount": 0,
      "_rbCount": 0,
      "_teCount": 0,
      "_olCount": 0,
      "_qbCount": 0
    },
    "event_2108fg0y": {
      "notes": "",
      "label": "",
      "player": "",
      "_wrCount": 0,
      "_rbCount": 0,
      "_teCount": 0,
      "_olCount": 0,
      "_qbCount": 0
    }
  },
  "overlays": {
    "play_i9ta4jbq": {
      "players": [],
      "los": null
    },
    "play_uq9djne0": {
      "players": [],
      "los": null
    },
    "event_2108fg0y": {
      "players": [],
      "los": null
    }
  }
}